four_color/__init__.py
four_color/__main__.py
four_color-0.5.1.dist-info/METADATA
four_color-0.5.1.dist-info/WHEEL
four_color-0.5.1.dist-info/licenses/LICENSE
four_color-0.5.1.dist-info/RECORD
