Metadata-Version: 2.3
Name: four_color
Version: 0.5.1
Summary: `four_color` is a package for Four Color Problem.
Project-URL: homepage, https://github.com/SaitoTsutomu/four_color
Author-email: Saito Tsutomu <tsutomu7@hotmail.co.jp>
License: Apache-2.0
License-File: LICENSE
Classifier: Development Status :: 1 - Planning
Classifier: License :: OSI Approved :: Apache Software License
Classifier: Programming Language :: Python
Classifier: Topic :: Scientific/Engineering
Classifier: Topic :: Software Development
Requires-Python: >=3.11
Requires-Dist: flask>=3.0.3
Requires-Dist: networkx>=3.3
Requires-Dist: pillow>=10.4.0
Requires-Dist: pulp>=2.9.0
